{
    "id": "cmpl-4B8YpAQtLNymeEPnPDEk0dUJQE813",
    "object": "text_completion",
    "created": 1638559863,
    "model": "davinci-codex:2021-08-03",
    "choices": [
        {
            "text": "\n    n, q = map(int, input().split())\n    a = list(map(int, input().split()))\n    for i in range(q):\n        x, y = map(int, input().split())\n        if x + y > n:\n            print(0)\n        else:\n            print(max(a[:x] + a[n - y:]))\n\ncode()",
            "index": 0,
            "logprobs": null,
            "finish_reason": "stop"
        },
        {
            "text": "\n    n, q = map(int, input().split())\n    a = list(map(int, input().split()))\n    for i in range(q):\n        x, y = map(int, input().split())\n        a[x:y+1] = [n+1]*(y-x+1)\n    print(a.count(n+1))\n\ncode()",
            "index": 1,
            "logprobs": null,
            "finish_reason": "stop"
        },
        {
            "text": "\n        # Solution 1 - 32 ms\n        ",
            "index": 2,
            "logprobs": null,
            "finish_reason": "stop"
        },
        {
            "text": "\n        res = \"\"\n        for i in range(len(indexes)):\n            if S[indexes[i]:indexes[i]+len(sources[i])] == sources[i]:\n                res += targets[i]\n                S = S[:indexes[i]] + S[indexes[i]+len(sources[i]):]\n            else:\n                res += S[indexes[i]]\n        res += S\n        return res",
            "index": 3,
            "logprobs": null,
            "finish_reason": "stop"
        },
        {
            "text": "\n        res = 0\n        while Y > X:\n            res += 1\n            if Y%2:\n                Y += 1\n            else:\n                Y //= 2\n        return res + X-Y",
            "index": 4,
            "logprobs": null,
            "finish_reason": "stop"
        },
        {
            "text": "\n        if X>=Y:\n            return X-Y\n        else:\n            if Y%2==0:\n                return 1+self.brokenCalc(X,Y//2)\n            else:\n                return 1+self.brokenCalc(X,Y+1)",
            "index": 5,
            "logprobs": null,
            "finish_reason": "stop"
        },
        {
            "text": "\n    n = int(input())\n    for i in range(n):\n        t = int(input())\n        print(sum(int(i) for i in str(2**t)))\n\nif __name__ == '__main__':\n    code()",
            "index": 6,
            "logprobs": null,
            "finish_reason": "stop"
        },
        {
            "text": "\n    n = int(input())\n    for i in range(n):\n        t = int(input())\n        sum = 0\n        while t > 0:\n            sum += t % 10\n            t //= 10\n        print(sum)\ncode()",
            "index": 7,
            "logprobs": null,
            "finish_reason": "stop"
        },
        {
            "text": "\n    ",
            "index": 8,
            "logprobs": null,
            "finish_reason": "stop"
        },
        {
            "text": "\n    num_sets = int(input())\n    for i in range(num_sets):\n        high_today, low_today, high_normal, low_normal = input().split()\n        high_today, low_today, high_normal, low_normal = int(high_today), int(low_today), int(high_normal), int(low_normal)\n        avg_diff = (high_today - high_normal) + (low_today - low_normal)\n        avg_diff = round(avg_diff / 2, 1)\n        if avg_diff > 0:\n            print(avg_diff, \"DEGREE(S) ABOVE NORMAL\")\n        elif avg_diff < 0:\n            print(abs(avg_diff), \"DEGREE(S) BELOW NORMAL\")\n        else:\n            print(avg_diff, \"DEGREE(S) ABOVE NORMAL\")\n\ncode()",
            "index": 9,
            "logprobs": null,
            "finish_reason": "stop"
        },
        {
            "text": "\n        return moves.count('U') == moves.count('D') and moves.count('L') == moves.count('R')",
            "index": 10,
            "logprobs": null,
            "finish_reason": "stop"
        },
        {
            "text": "\n        x = 0\n        y = 0\n        for move in moves:\n            if move == 'U':\n                y += 1\n            elif move == 'D':\n                y -= 1\n            elif move == 'L':\n                x -= 1\n            elif move == 'R':\n                x += 1\n        return x == 0 and y == 0",
            "index": 11,
            "logprobs": null,
            "finish_reason": "stop"
        },
        {
            "text": "\n    t = int(input())\n    for i in range(t):\n        p, q = map(int, input().split())\n        while p % q != 0:\n            p += 1\n        print(p)\n\ncode()",
            "index": 12,
            "logprobs": null,
            "finish_reason": "stop"
        },
        {
            "text": "\n    t = int(input())\n    for i in range(t):\n        p, q = map(int, input().split())\n        while p % q == 0:\n            p //= q\n        print(p)\n\ncode()",
            "index": 13,
            "logprobs": null,
            "finish_reason": "stop"
        },
        {
            "text": "\n    s = input()\n    n = int(input())\n    for i in range(n):\n        d, t = input().split('->')\n        s = s.replace(d, t)\n    print(int(s)%1000000007)\n\ncode()",
            "index": 14,
            "logprobs": null,
            "finish_reason": "stop"
        },
        {
            "text": "\n    s = input()\n    n = int(input())\n    for i in range(n):\n        d, t = input().split('->')\n        s = s.replace(d, t)\n    print(int(s) % 1000000007)\n\ncode()",
            "index": 15,
            "logprobs": null,
            "finish_reason": "stop"
        },
        {
            "text": "\n    T = int(input())\n    for i in range(T):\n        s = input()\n        if s == s[::-1]:\n            print(\"YES\")\n        else:\n            print(\"NO\")\ncode()",
            "index": 16,
            "logprobs": null,
            "finish_reason": "stop"
        },
        {
            "text": "\n    T = int(input())\n    for i in range(T):\n        s = input()\n        if s == s[::-1]:\n            print(\"YES\")\n        else:\n            print(\"NO\")\n\ncode()",
            "index": 17,
            "logprobs": null,
            "finish_reason": "stop"
        },
        {
            "text": "\n    n = int(input())\n    a = list(map(int, input().split()))\n    a.sort()\n    i = 0\n    j = n - 1\n    count = 0\n    while i < j:\n        if a[i] + a[j] <= 2:\n            count += 1\n            i += 1\n            j -= 1\n        else:\n            count += 1\n            j -= 1\n    if i == j:\n        count += 1\n    print(count)\n\ncode()",
            "index": 18,
            "logprobs": null,
            "finish_reason": "stop"
        },
        {
            "text": "\n    n = int(input())\n    a = list(map(int, input().split()))\n    d = {}\n    for i in a:\n        if i in d:\n            d[i] += 1\n        else:\n            d[i] = 1\n    count = 0\n    for i in d:\n        if d[i] > 2:\n            count += d[i] - 2\n    print(count)\n\ncode()",
            "index": 19,
            "logprobs": null,
            "finish_reason": "stop"
        }
    ]
}