{
    "0": "\n    n = int(input())\n    a = list(map(int, input().split()))\n    a.sort()\n    a.append(0)\n    ans = 0\n    for i in range(n):\n        if a[i] != a[i+1]:\n            ans += 1\n    print(ans)\n",
    "1": "\n    n = int(input())\n    a = list(map(int, input().split()))\n    d = {}\n    for i in range(n):\n        for j in range(i, n):\n            d[a[i] | a[j]] = 1\n    print(len(d))\n",
    "2": "\n        if not board:\n            return 0\n        count = 0\n        for i in range(len(board)):\n            for j in range(len(board[0])):\n                if board[i][j] == 'X':\n                    if i > 0 and board[i-1][j] == 'X':\n                        continue\n                    if j > 0 and board[i][j-1] == 'X':\n                        continue\n                    count += 1\n        return count",
    "3": "\n        if not board:\n            return 0\n        count = 0\n        for i in range(len(board)):\n            for j in range(len(board[0])):\n                if board[i][j] == 'X':\n                    if i > 0 and board[i-1][j] == 'X':\n                        continue\n                    if j > 0 and board[i][j-1] == 'X':\n                        continue\n                    count += 1\n        return count",
    "4": "\n    s = list(s)\n    for i in range(len(s)):\n        if s[i].isupper():\n            s[i] = s[i].lower()\n        else:\n            s[i] = s[i].upper()\n    return ''.join(s)\n\nprint(sc(\"Aab\"))\nprint(sc(\"AabBc\"))\nprint(sc(\"AaaaAaab\"))\nprint(sc(\"aAAAaAAb\"))",
    "5": "\n    return ''.join(sorted(set(s), key=s.index))",
    "6": "\n    return n * (n + 1) // 2\n\nprint(rocks(13))",
    "7": "\n    return n * (n + 1) // 2\n\nprint(rocks(13))",
    "8": "\n    if not words:\n        return {}\n    if not words[0]:\n        return {}\n    if len(words) == 1:\n        return {words[0]: {}}\n    root = {}\n    for word in words:\n        current = root\n        for letter in word:\n            if letter not in current:\n                current[letter] = {}\n            current = current[letter]\n        current[\"\"] = {}\n    return root",
    "9": "\n    pass",
    "10": "\n    n, s = map(int, input().split())\n    a = list(map(int, input().split()))\n    a.sort()\n    if a[n//2] == s:\n        print(0)\n    elif a[n//2] < s:\n        print(s - a[n//2])\n    else:\n        print(a[n//2] - s)\n",
    "11": "\n    n, s = map(int, input().split())\n    a = list(map(int, input().split()))\n    a.sort()\n    if a[n//2] == s:\n        print(0)\n    elif a[n//2] < s:\n        print(s - a[n//2])\n    else:\n        print(a[n//2] - s)\n",
    "12": "\n    return sorted(set(santas_list).intersection(children))",
    "13": "\n    return sorted(set(santas_list).intersection(children))",
    "14": "\n    even = []\n    odd = []\n    for i in integers:\n        if i % 2 == 0:\n            even.append(i)\n        else:\n            odd.append(i)\n    if len(even) == 1:\n        return even[0]\n    else:\n        return odd[0]",
    "15": "\n    even = []\n    odd = []\n    for i in integers:\n        if i % 2 == 0:\n            even.append(i)\n        else:\n            odd.append(i)\n    if len(even) > len(odd):\n        return odd[0]\n    else:\n        return even[0]",
    "16": "\n    t = int(input())\n    for i in range(t):\n        a1, b1 = map(int, input().split())\n        a2, b2 = map(int, input().split())\n        if a1 == a2 or b1 == b2:\n            print(\"Yes\")\n        else:\n            print(\"No\")\n",
    "17": "\n    t = int(input())\n    for i in range(t):\n        a1, b1 = map(int, input().split())\n        a2, b2 = map(int, input().split())\n        if a1 == a2 or b1 == b2:\n            print(\"Yes\")\n        elif a1 == b2 or b1 == a2:\n            print(\"Yes\")\n        else:\n            print(\"No\")\n",
    "18": "\n        if not head:\n            return None\n        if m == n:\n            return head\n        dummy = ListNode(0)\n        dummy.next = head\n        pre = dummy\n        for i in range(m-1):\n            pre = pre.next\n        cur = pre.next\n        for i in range(n-m):\n            temp = cur.next\n            cur.next = temp.next\n            temp.next = pre.next\n            pre.next = temp\n        return dummy.next",
    "19": "\n        if not head:\n            return None\n        if m == n:\n            return head\n        dummy = ListNode(0)\n        dummy.next = head\n        pre = dummy\n        for i in range(m-1):\n            pre = pre.next\n        cur = pre.next\n        for i in range(n-m):\n            temp = cur.next\n            cur.next = temp.next\n            temp.next = pre.next\n            pre.next = temp\n        return dummy.next"
}