["database = '''werewolf : Silver knife or bullet to the heart\nvampire : Behead it with a machete\nwendigo : Burn it to death\nshapeshifter : Silver knife or bullet to the heart\nangel : Use the angelic blade\ndemon : Use Ruby's knife, or some Jesus-juice\nghost : Salt and iron, and don't forget to burn the corpse\ndragon : You have to find the excalibur for that\ndjinn : Stab it with silver knife dipped in a lamb's blood\npagan god : It depends on which one it is\nleviathan : Use some Borax, then kill Dick\nghoul : Behead it\njefferson starship : Behead it with a silver blade\nreaper : If it's nasty, you should gank who controls it\nrugaru : Burn it alive\nskinwalker : A silver bullet will do it\nphoenix : Use the colt\nwitch : They are humans\nelse : I have friggin no idea yet'''\n\nanswers = {line.split(' : ')[0]:line.split(' : ')[1] for line in database.splitlines()}\n\ndef bob(what):\n    return answers.get(what, answers['else'])+', idjits!'", "def bob(what):\n    db = {}\n    db[\"werewolf\"] = \"Silver knife or bullet to the heart\"\n    db[\"vampire\"] = \"Behead it with a machete\"\n    db[\"wendigo\"] = \"Burn it to death\"\n    db[\"shapeshifter\"] = \"Silver knife or bullet to the heart\"\n    db[\"angel\"] = \"Use the angelic blade\"\n    db[\"demon\"] = \"Use Ruby's knife, or some Jesus-juice\"\n    db[\"ghost\"] = \"Salt and iron, and don't forget to burn the corpse\"\n    db[\"dragon\"] = \"You have to find the excalibur for that\"\n    db[\"djinn\"] = \"Stab it with silver knife dipped in a lamb's blood\"\n    db[\"pagan god\"] = \"It depends on which one it is\"\n    db[\"leviathan\"] = \"Use some Borax, then kill Dick\"\n    db[\"ghoul\"] = \"Behead it\"\n    db[\"jefferson starship\"] = \"Behead it with a silver blade\"\n    db[\"reaper\"] = \"If it's nasty, you should gank who controls it\"\n    db[\"rugaru\"] = \"Burn it alive\"\n    db[\"skinwalker\"] = \"A silver bullet will do it\"\n    db[\"phoenix\"] = \"Use the colt\"\n    db[\"witch\"] = \"They are humans\"\n    if what in db:\n      return db[what]+\", idjits!\"\n    else:\n      return \"I have friggin no idea yet\"+\", idjits!\"", "database = {\n    \"werewolf\" : \"Silver knife or bullet to the heart\",\n    \"vampire\" :  \"Behead it with a machete\",\n    \"wendigo\" :  \"Burn it to death\",\n    \"shapeshifter\" : \"Silver knife or bullet to the heart\",\n    \"angel\" :  \"Use the angelic blade\",\n    \"demon\" :  \"Use Ruby's knife, or some Jesus-juice\",\n    \"ghost\" :  \"Salt and iron, and don't forget to burn the corpse\",\n    \"dragon\" :  \"You have to find the excalibur for that\",\n    \"djinn\" :  \"Stab it with silver knife dipped in a lamb's blood\",\n    \"pagan god\" :  \"It depends on which one it is\",\n    \"leviathan\" :  \"Use some Borax, then kill Dick\",\n    \"ghoul\" : \"Behead it\",\n    \"jefferson starship\": \"Behead it with a silver blade\",\n    \"reaper\": \"If it's nasty, you should gank who controls it\",\n    \"rugaru\": \"Burn it alive\",\n    \"skinwalker\": \"A silver bullet will do it\",\n    \"phoenix\": \"Use the colt\",\n    \"witch\": \"They are humans\",\n}\ndef bob(what):\n    default = \"I have friggin no idea yet\"\n    return database.get(what, default) + \", idjits!\""]