{"0": [[false, true, false, true, true, true, true, true, true, true, true, false, false]], "1": [[false, true, false, false, true, true, true, false, false, false, false, false, false]], "2": [[true]], "3": [[true]], "4": [[-1]], "5": [[-1]], "6": [[-2]], "7": [[-2]], "8": [[false, true, false, false, true, true, false, false, true, true, true, false, true]], "9": [[false, true, false, false, false, true, false, false, false, false, false, false, true]], "10": [[-2]], "11": [[-2]], "12": [[true]], "13": [[true]], "14": [[true, false, false, false, false, false, false, false, false, false, false, true, false, false]], "15": [[false, false, false, false, false, false, false, false, false, false, false, false, false, false]], "16": [[-2]], "17": [[-2]], "18": [[true, true, true, true, true, true, true, true, true, true, -1, true, true, true, -1]], "19": [[true, true, true, true, true, true, true, true, true, true, -1, true, true, true, -1]]}